Attendance/__init__.py
Attendance/app.py
Attendance/attendance.py
Attendance/config.py
Attendance/database.py
Attendance/database_s3.py
Attendance/external_connector.py
Attendance/static/student-view.html
Attendance/static/teacher-view.html
Attendance/static/test.html
Attendance/static/images/2620267.png
Attendance/static/images/favicon-16x16.png
Attendance/static/images/favicon-32x32.png
Attendance/static/images/favicon.ico
Attendance/static/scripts/index.js
Attendance/static/scripts/jquery.js
Attendance/static/scripts/nicepage.js
Attendance/static/style/Post-Template.css
Attendance/static/style/Student-View.css
Attendance/static/style/Teacher-View.css
Attendance/static/style/nicepage.css
test/__init__.py
test/backend_integration/__init__.py
test/backend_integration/test_database_s3.py
test/backend_unit/__init__.py
test/backend_unit/test_attendance.py
test/backend_unit/test_config.py
test/backend_unit/test_database.py
test/backend_unit/test_database_s3.py
test/backend_unit/test_external_connector.py
CSCN73030_Attendance_Module-0.18.0.dist-info/METADATA
CSCN73030_Attendance_Module-0.18.0.dist-info/WHEEL
CSCN73030_Attendance_Module-0.18.0.dist-info/top_level.txt
CSCN73030_Attendance_Module-0.18.0.dist-info/RECORD
