Metadata-Version: 2.1
Name: CSCN73030-Attendance-Module
Version: 0.18.0
Summary: An Attendance webapp component created for the CSCN73030 at Conestoga College, Ontario, Canada
Home-page: https://github.com/CSCN73030-projectv-group9/Attendance
Author: Emil Harvey
Author-email: eharvey3704@conestogac.on.ca
Project-URL: Bug Reports, https://github.com/CSCN73030-projectv-group9/Attendance/issues
Project-URL: Source, https://github.com/CSCN73030-projectv-group9/Attendance
Requires-Python: >=3.7, <4
Requires-Dist: flask
Requires-Dist: pydantic
Requires-Dist: flask-cors
Requires-Dist: gitpython
Requires-Dist: pyyaml
Requires-Dist: requests
Requires-Dist: boto3
Requires-Dist: botocore
Provides-Extra: test
Requires-Dist: coverage ; extra == 'test'
Requires-Dist: pytest ; extra == 'test'
